riscos_dump/__init__.py
riscos_dump/__main__.py
riscos_dump/dump.py
riscos_dump/wxdump.py
riscos_dump/wxdumper.py
riscos_dump-0.2.0.dist-info/LICENSE
riscos_dump-0.2.0.dist-info/METADATA
riscos_dump-0.2.0.dist-info/WHEEL
riscos_dump-0.2.0.dist-info/entry_points.txt
riscos_dump-0.2.0.dist-info/top_level.txt
riscos_dump-0.2.0.dist-info/RECORD
